meta_ml-0.0.24.data/scripts/metalearn
metalearn/__init__.py
metalearn/algorithm_env.py
metalearn/algorithm_space.py
metalearn/beam_search.py
metalearn/data_types.py
metalearn/enforce_fit_limits.py
metalearn/errors.py
metalearn/evaluate.py
metalearn/evaluate_code_generator.py
metalearn/experiment.py
metalearn/ignore_warnings.py
metalearn/loggers.py
metalearn/metalearn_controller.py
metalearn/metalearn_reinforce.py
metalearn/plotting.py
metalearn/random_search.py
metalearn/rnn_code_generator.py
metalearn/scorers.py
metalearn/task_environment.py
metalearn/tracking.py
metalearn/utils.py
metalearn/components/__init__.py
metalearn/components/algorithm_component.py
metalearn/components/classifiers.py
metalearn/components/constants.py
metalearn/components/data_preprocessors.py
metalearn/components/feature_preprocessors.py
metalearn/components/hyperparameter.py
metalearn/components/regressors.py
metalearn/data_environments/__init__.py
metalearn/data_environments/autosklearn_clf_task_ids.py
metalearn/data_environments/data_environment.py
metalearn/data_environments/environments.py
metalearn/data_environments/kaggle_api.py
metalearn/data_environments/kaggle_base.py
metalearn/data_environments/kaggle_classification.py
metalearn/data_environments/kaggle_regression.py
metalearn/data_environments/openml_api.py
metalearn/data_environments/sklearn_classification.py
metalearn/data_environments/sklearn_regression.py
metalearn/data_environments/feature_maps/__init__.py
metalearn/data_environments/feature_maps/kaggle_costa_rican_household_poverty_prediction.py
metalearn/data_environments/feature_maps/kaggle_homesite_quote_conversion.py
metalearn/data_environments/feature_maps/kaggle_santander_customer_satisfaction.py
metalearn/inference/__init__.py
metalearn/inference/inference_engine.py
meta_ml-0.0.24.dist-info/METADATA
meta_ml-0.0.24.dist-info/WHEEL
meta_ml-0.0.24.dist-info/top_level.txt
meta_ml-0.0.24.dist-info/RECORD
