Metadata-Version: 2.1
Name: meta-ml
Version: 0.0.24
Summary: MetaRL-based Estimator using Task-encodings for AutoML
Home-page: https://github.com/cosmicBboy/ml-research/tree/master/metalearn
License: UNKNOWN
Platform: UNKNOWN
Requires-Dist: click (==7.0)
Requires-Dist: dill (==0.3.1.1)
Requires-Dist: numpy
Requires-Dist: pandas (==1.0.5)
Requires-Dist: torch (==1.5.0)
Requires-Dist: scipy
Provides-Extra: all
Requires-Dist: kaggle ; extra == 'all'
Requires-Dist: openml (==0.9.0) ; extra == 'all'
Requires-Dist: psutil ; extra == 'all'
Requires-Dist: scikit-learn (>=0.21.2) ; extra == 'all'
Requires-Dist: yamlordereddictloader ; extra == 'all'
Provides-Extra: experiments
Requires-Dist: yamlordereddictloader ; extra == 'experiments'
Provides-Extra: sklearn
Requires-Dist: scikit-learn (>=0.21.2) ; extra == 'sklearn'
Provides-Extra: tasks
Requires-Dist: openml (==0.9.0) ; extra == 'tasks'
Requires-Dist: kaggle ; extra == 'tasks'
Requires-Dist: psutil ; extra == 'tasks'
